pyalect/__init__.py
pyalect/dialect.py
pyalect/errors.py
pyalect/importer.py
pyalect/py.typed
pyalect/shims.py
pyalect/builtins/__init__.py
pyalect/builtins/pytest.py
pyalect-0.1.0.dist-info/LICENSE
pyalect-0.1.0.dist-info/METADATA
pyalect-0.1.0.dist-info/WHEEL
pyalect-0.1.0.dist-info/top_level.txt
pyalect-0.1.0.dist-info/RECORD
